{
  "$schema": "https://developer.microsoft.com/json-schemas/fabric/item/report/definition/visualContainer/2.10.0/schema.json",
  "name": "e7c73867bb304fc4319a",
  "position": {
    "x": 310,
    "y": 52,
    "z": 10050,
    "height": 15,
    "width": 680,
    "tabOrder": 10050
  },
  "visual": {
    "visualType": "textbox",
    "objects": {
      "general": [
        {
          "properties": {
            "paragraphs": [
              {
                "textRuns": [
                  {
                    "value": "Historical transfer fees  |  Market value movements  |  Season & position analysis",
                    "textStyle": {
                      "fontWeight": "normal",
                      "fontSize": "7.5pt",
                      "color": "#C8F5C0"
                    }
                  }
                ]
              }
            ]
          }
        }
      ]
    },
    "visualContainerObjects": {
      "background": [
        {
          "properties": {
            "show": {
              "expr": {
                "Literal": {
                  "Value": "false"
                }
              }
            }
          }
        }
      ]
    },
    "drillFilterOtherVisuals": true
  }
}